lazycode/__init__.py
lazycode/__version__.py
lazycode/setting.py
lazycode/core/BaseType.py
lazycode/core/LzBean.py
lazycode/core/LzConcurrence.py
lazycode/core/LzDataFrame.py
lazycode/core/LzDataTypeMap.py
lazycode/core/LzDateTime.py
lazycode/core/LzElasticsearch.py
lazycode/core/LzEmail.py
lazycode/core/LzFileDir.py
lazycode/core/LzHttpClient.py
lazycode/core/LzJsonPath.py
lazycode/core/LzKafka.py
lazycode/core/LzLinux.py
lazycode/core/LzList.py
lazycode/core/LzMap.py
lazycode/core/LzMongoDB.py
lazycode/core/LzMySQL.py
lazycode/core/LzNumber.py
lazycode/core/LzRandom.py
lazycode/core/LzRandomData.py
lazycode/core/LzRedis.py
lazycode/core/LzScheduler.py
lazycode/core/LzSerialize.py
lazycode/core/LzString.py
lazycode/core/LzTypeCheck.py
lazycode/core/__init__.py
lazycode/decorator/__init__.py
lazycode/decorator/decorator.py
lazycode/decorator/logging.py
lazycode/tool/LzGit.py
lazycode/tool/__init__.py
lazycode/tool/create_file_tree.py
lazycode/tool/relative_to_absolutely_path.py
lazycode-1.1.1.dist-info/LICENSE
lazycode-1.1.1.dist-info/METADATA
lazycode-1.1.1.dist-info/WHEEL
lazycode-1.1.1.dist-info/top_level.txt
lazycode-1.1.1.dist-info/RECORD
